README
setup.py
fun3dapi/__init__.py
fun3dapi/fun3dapi.py
fun3dapi/htserver.py
fun3dapi/mylogger.py
fun3dapi/rest.py
fun3dapi.egg-info/PKG-INFO
fun3dapi.egg-info/SOURCES.txt
fun3dapi.egg-info/dependency_links.txt
fun3dapi.egg-info/requires.txt
fun3dapi.egg-info/top_level.txt