Metadata-Version: 1.0
Name: fun3dapi
Version: 0.1
Summary: A Python API for high-throughput FUN3D
Home-page: UNKNOWN
Author: FlexCompute, Inc.
Author-email: john@simulation.cloud
License: UNKNOWN
Platform: UNKNOWN
